lamp/__init__.py
lamp/__main__.py
lamp/anno.py
lamp/gui.py
lamp/stats.py
lamp/utils.py
lamp/lib/.DS_Store
lamp/lib/GSMM_LAMP_ReferenceFile_v1_281024.xlsx
lamp/lib/adducts.txt
lamp/lib/nist_database.txt
lamp/qt/__init__.py
lamp/qt/lamp_form.py
lamps-1.0.4.dist-info/licenses/LICENSE
lamps-1.0.4.dist-info/METADATA
lamps-1.0.4.dist-info/WHEEL
lamps-1.0.4.dist-info/entry_points.txt
lamps-1.0.4.dist-info/top_level.txt
lamps-1.0.4.dist-info/RECORD
