Metadata-Version: 2.4
Name: lamps
Version: 1.0.4
Summary: Liverpool Annotation of metabolites using Mass Spectrometry
Author-email: Wanchang Lin <wanchang.lin@liverpool.ac.uk>, Warwick Dunn <warwick.dunn@liverpool.ac.uk>
Maintainer-email: Wanchang Lin <wanchang.lin@liverpool.ac.uk>
License:                     GNU GENERAL PUBLIC LICENSE
Project-URL: Homepage, https://github.com/wanchanglin/lamp
Project-URL: Issues, https://github.com/wanchanglin/lamp/issues
Project-URL: Documentation, https://lamp-liverpool-annotation-of-metabolite-using-mass-spectrometry.readthedocs.io/en/latest/
Keywords: Metabolomics,Metabolite Annotation,Mass spectrometry,Liquid-Chromatography Mass Spectrometry
Classifier: Programming Language :: Python :: 3
Classifier: License :: OSI Approved :: GNU General Public License v3 (GPLv3)
Classifier: Operating System :: OS Independent
Requires-Python: >=3.8
License-File: LICENSE
Requires-Dist: numpy
Requires-Dist: scipy
Requires-Dist: pandas
Requires-Dist: pyside6
Requires-Dist: pyteomics
Requires-Dist: openpyxl
Requires-Dist: pyjanitor
Dynamic: license-file
